ecbdata/__about__.py
ecbdata/__init__.py
ecbdata/api.py
ecbdata/tests/__init__.py
ecbdata/tests/test.py
ecbdata-0.1.1.dist-info/LICENSE.md
ecbdata-0.1.1.dist-info/METADATA
ecbdata-0.1.1.dist-info/WHEEL
ecbdata-0.1.1.dist-info/top_level.txt
ecbdata-0.1.1.dist-info/RECORD
