Metadata-Version: 2.1
Name: ecbdata
Version: 0.1.1
Summary: The ecbdata API allows for easy querying of data from the ECB Data Portal: https://data.ecb.europa.eu/help/data/overview.
Home-page: https://github.com/LucaMingarelli/ecbdata
Author: Luca Mingarelli
Author-email: luca.mingarelli@ecb.europa.eu
License: MIT
Classifier: Programming Language :: Python :: 3
Classifier: License :: OSI Approved :: MIT License
Classifier: Operating System :: OS Independent
Requires-Python: >=3.6
License-File: LICENSE.md
Requires-Dist: setuptools
Requires-Dist: requests
Requires-Dist: pandas
